{
  "cli": {
    "version": ">= 16.26.0",
    "appVersionSource": "remote"
  },
  "build": {
    "development": {
      "developmentClient": true,
      "distribution": "internal",
      "env": {
        "EXPO_PUBLIC_GEMINI_API_KEY": "AIzaSyCwAud8om_isV8yPW15DeS-_bOiudp-NzA"
      }
    },
    "preview": {
      "distribution": "internal",
      "android": {
        "buildType": "apk"
      },
      "env": {
        "EXPO_PUBLIC_GEMINI_API_KEY": "AIzaSyCwAud8om_isV8yPW15DeS-_bOiudp-NzA"
      }
    },
    "production": {
      "autoIncrement": true,
      "android": {
        "buildType": "apk"
      },
      "env": {
        "EXPO_PUBLIC_GEMINI_API_KEY": "AIzaSyCwAud8om_isV8yPW15DeS-_bOiudp-NzA"
      }
    }
  },
  "submit": {
    "production": {}
  }
}
